{"cameraMode":{"drawMode":0,"name":"Shaded","section":"Shading Mode"},"sceneLighting":true,"audioPlay":false,"sceneViewState":{"m_AlwaysRefresh":false,"showFog":true,"showSkybox":true,"showFlares":true,"showImageEffects":true,"showParticleSystems":true,"showVisualEffectGraphs":true,"m_FxEnabled":true},"in2DMode":false,"pivot":{"x":-0.03991051763296127,"y":1.2578104734420777,"z":-0.4472137689590454},"rotation":{"x":-0.14820332825183869,"y":-0.02759103663265705,"z":0.004136511590331793,"w":-0.9885650873184204},"size":1.1660256385803223,"orthographic":false}